video_understanding/__init__.py
video_understanding/video_understanding.py
video_understanding-0.1.1.dist-info/METADATA
video_understanding-0.1.1.dist-info/WHEEL
video_understanding-0.1.1.dist-info/RECORD
