Metadata-Version: 2.4
Name: video_understanding
Version: 0.1.1
Summary: Understand and describe your videos with SmolVLM2, Whisper and Qwen. Fully local.
Project-URL: Homepage, https://github.com/Grigorij-Dudnik/video-understanding-local
Project-URL: Issues, https://github.com/Grigorij-Dudnik/video-understanding-local/issues
Author-email: Grigorij Dudnik <dudnikgrv@gmail.com>
License-Expression: MIT
Classifier: Operating System :: OS Independent
Classifier: Programming Language :: Python :: 3
Requires-Python: >=3.10
Requires-Dist: accelerate>=1.10.1
Requires-Dist: av>=15.1.0
Requires-Dist: num2words>=0.5.14
Requires-Dist: openai-whisper>=20250625
Requires-Dist: pillow>=11.3.0
Requires-Dist: torchcodec>=0.7.0
Requires-Dist: torchvision>=0.23.0
Requires-Dist: transformers>=4.56.2
